strict_types/__init__.py
strict_types/checker.py
flake8_strict_types-0.1.4.dist-info/METADATA
flake8_strict_types-0.1.4.dist-info/WHEEL
flake8_strict_types-0.1.4.dist-info/entry_points.txt
flake8_strict_types-0.1.4.dist-info/licenses/LICENSE.md
flake8_strict_types-0.1.4.dist-info/RECORD
